[{"name":"African Sun Limited","open":0.0437,"close":0.0443,"volume":1600},{"name":"Axia Corporation Limited","open":0.08,"close":0.0799,"volume":13671},{"name":"Caledonia Mining Corporation Plc","open":11.85,"close":11.85,"volume":0},{"name":"Edgars Stores Limited","open":0.0102,"close":0.0102,"volume":0},{"name":"First Capital Bank Limited","open":0.0489,"close":0.0487,"volume":697},{"name":"Innscor Africa Limited","open":0.45,"close":0.4502,"volume":3014},{"name":"Invictus Energy Zdrs","open":0.08,"close":0.08,"volume":0},{"name":"National Foods Holdings Ltd","open":1.92,"close":1.92,"volume":10},{"name":"Nedbank Group Limited Zimbabwe Depository Receipts","open":12,"close":12,"volume":0},{"name":"Padenga Holdings Ltd","open":0.1798,"close":0.1799,"volume":22064},{"name":"Seed Co International Vx","open":0.21,"close":0.21,"volume":2767},{"name":"Simbisa Brands Limited","open":0.317,"close":0.34,"volume":3885},{"name":"West Prop Holdings Limited","open":10.05,"close":10.05,"volume":0},{"name":"Zimplow Holdings Limited","open":0.0136,"close":0.0138,"volume":300}]